Workbook

Sheet OPCS4_codesall
A1: Operation OPCS-4 Code | B1: n | C1: Percentage abundance (%) | D1: Description
A2: Z943 | B2: 70 | C2: =(B2/726)*100 -> 9.6418733 | D2: =_xlfn.XLOOKUP(A2,'OPCS49 CodesAndTitles Nov 2019 '!A:A, 'OPCS49 CodesAndTitles Nov 2019 '!B:B) -> Left sided operation
A3: Z942 | B3: 68 | C3: =(B3/726)*100 -> 9.3663912 | D3: =_xlfn.XLOOKUP(A3,'OPCS49 CodesAndTitles Nov 2019 '!A:A, 'OPCS49 CodesAndTitles Nov 2019 '!B:B) -> Right sided operation
A4: Z765 | B4: 45 | C4: =(B4/726)*100 -> 6.1983471 | D4: =_xlfn.XLOOKUP(A4,'OPCS49 CodesAndTitles Nov 2019 '!A:A, 'OPCS49 CodesAndTitles Nov 2019 '!B:B) -> Lower end of femur NEC
A5: Y981 | B5: 39 | C5: =(B5/726)*100 -> 5.3719008 | D5: =_xlfn.XLOOKUP(A5,'OPCS49 CodesAndTitles Nov 2019 '!A:A, 'OPCS49 CodesAndTitles Nov 2019 '!B:B) -> Radiology of one body area (or < 20 minutes)
A6: W201 | B6: 30 | C6: =(B6/726)*100 -> 4.1322314 | D6: =_xlfn.XLOOKUP(A6,'OPCS49 CodesAndTitles Nov 2019 '!A:A, 'OPCS49 CodesAndTitles Nov 2019 '!B:B) -> Primary open reduction of fracture of long bone and extramedullary fixation using plate NEC
A7: X364 | B7: 26 | C7: =(B7/726)*100 -> 3.5812672 | D7: =_xlfn.XLOOKUP(A7,'OPCS49 CodesAndTitles Nov 2019 '!A:A, 'OPCS49 CodesAndTitles Nov 2019 '!B:B) -> Autologous blood salvage
A8: X337 | B8: 24 | C8: =(B8/726)*100 -> 3.3057851 | D8: =_xlfn.XLOOKUP(A8,'OPCS49 CodesAndTitles Nov 2019 '!A:A, 'OPCS49 CodesAndTitles Nov 2019 '!B:B) -> Autologous transfusion of red blood cells
A9: W403 | B9: 22 | C9: =(B9/726)*100 -> 3.030303 | D9: =_xlfn.XLOOKUP(A9,'OPCS49 CodesAndTitles Nov 2019 '!A:A, 'OPCS49 CodesAndTitles Nov 2019 '!B:B) -> Revision of total prosthetic replacement of knee joint using cement
A10: Z846 | B10: 22 | C10: =(B10/726)*100 -> 3.030303 | D10: =_xlfn.XLOOKUP(A10,'OPCS49 CodesAndTitles Nov 2019 '!A:A, 'OPCS49 CodesAndTitles Nov 2019 '!B:B) -> Knee joint
A11: U212 | B11: 18 | C11: =(B11/726)*100 -> 2.4793388 | D11: =_xlfn.XLOOKUP(A11,'OPCS49 CodesAndTitles Nov 2019 '!A:A, 'OPCS49 CodesAndTitles Nov 2019 '!B:B) -> Computed tomography NEC
A12: U136 | B12: 17 | C12: =(B12/726)*100 -> 2.3415978 | D12: =_xlfn.XLOOKUP(A12,'OPCS49 CodesAndTitles Nov 2019 '!A:A, 'OPCS49 CodesAndTitles Nov 2019 '!B:B) -> Computed tomography of bone
A13: M479 | B13: 14 | C13: =(B13/726)*100 -> 1.9283747 | D13: =_xlfn.XLOOKUP(A13,'OPCS49 CodesAndTitles Nov 2019 '!A:A, 'OPCS49 CodesAndTitles Nov 2019 '!B:B) -> Unspecified urethral catheterisation of bladder
... A140: Z988 | B140: 1 | C140: =(B140/726)*100 -> 0.13774105 | D140: =_xlfn.XLOOKUP(A140,'OPCS49 CodesAndTitles Nov 2019 '!A:A, 'OPCS49 CodesAndTitles Nov 2019 '!B:B) -> Specified vein of lower limb NEC

Sheet OPCS49 CodesAndTitles Nov 2019 
A1: Column1 | B1: Column2
A2: A01 | B2: Major excision of tissue of brain
A3: A011 | B3: Hemispherectomy
A4: A012 | B4: Total lobectomy of brain
A5: A013 | B5: Partial lobectomy of brain
A6: A018 | B6: Other specified major excision of tissue of brain
A7: A019 | B7: Unspecified major excision of tissue of brain
A8: A02 | B8: Excision of lesion of tissue of brain
A9: A021 | B9: Excision of lesion of tissue of frontal lobe of brain
A10: A022 | B10: Excision of lesion of tissue of temporal lobe of brain
A11: A023 | B11: Excision of lesion of tissue of parietal lobe of brain
A12: A024 | B12: Excision of lesion of tissue of occipital lobe of brain
... A11252: O459 | B11252: Other aorta NEC
